main.py
setup.py
mnolith.egg-info/PKG-INFO
mnolith.egg-info/SOURCES.txt
mnolith.egg-info/dependency_links.txt
mnolith.egg-info/requires.txt
mnolith.egg-info/top_level.txt